<INVENTORY>
	<ITEM>
		<ITEMTYPE>P</ITEMTYPE>
		<ITEMID>32009</ITEMID>
		<COLOR>1</COLOR>
		<MINQTY>10</MINQTY>
	</ITEM>
	<ITEM>
		<ITEMTYPE>P</ITEMTYPE>
		<ITEMID>32013</ITEMID>
		<COLOR>11</COLOR>
		<MINQTY>14</MINQTY>
	</ITEM>
	<ITEM>
		<ITEMTYPE>P</ITEMTYPE>
		<ITEMID>32014</ITEMID>
		<COLOR>11</COLOR>
		<MINQTY>6</MINQTY>
	</ITEM>
	<ITEM>
		<ITEMTYPE>P</ITEMTYPE>
		<ITEMID>32034</ITEMID>
		<COLOR>11</COLOR>
		<MINQTY>13</MINQTY>
	</ITEM>
	<ITEM>
		<ITEMTYPE>P</ITEMTYPE>
		<ITEMID>32054</ITEMID>
		<COLOR>5</COLOR>
		<MINQTY>46</MINQTY>
	</ITEM>
	<ITEM>
		<ITEMTYPE>P</ITEMTYPE>
		<ITEMID>32062</ITEMID>
		<COLOR>5</COLOR>
		<MINQTY>43</MINQTY>
	</ITEM>
	<ITEM>
		<ITEMTYPE>P</ITEMTYPE>
		<ITEMID>32073</ITEMID>
		<COLOR>86</COLOR>
		<MINQTY>20</MINQTY>
	</ITEM>
	<ITEM>
		<ITEMTYPE>P</ITEMTYPE>
		<ITEMID>32140</ITEMID>
		<COLOR>5</COLOR>
		<MINQTY>16</MINQTY>
	</ITEM>
	<ITEM>
		<ITEMTYPE>P</ITEMTYPE>
		<ITEMID>32348</ITEMID>
		<COLOR>1</COLOR>
		<MINQTY>11</MINQTY>
	</ITEM>
	<ITEM>
		<ITEMTYPE>P</ITEMTYPE>
		<ITEMID>3648</ITEMID>
		<COLOR>85</COLOR>
		<MINQTY>10</MINQTY>
	</ITEM>
	<ITEM>
		<ITEMTYPE>P</ITEMTYPE>
		<ITEMID>3649</ITEMID>
		<COLOR>86</COLOR>
		<MINQTY>6</MINQTY>
	</ITEM>
	<ITEM>
		<ITEMTYPE>P</ITEMTYPE>
		<ITEMID>3673</ITEMID>
		<COLOR>86</COLOR>
		<MINQTY>22</MINQTY>
	</ITEM>
	<ITEM>
		<ITEMTYPE>P</ITEMTYPE>
		<ITEMID>3705</ITEMID>
		<COLOR>11</COLOR>
		<MINQTY>13</MINQTY>
	</ITEM>
	<ITEM>
		<ITEMTYPE>P</ITEMTYPE>
		<ITEMID>3706</ITEMID>
		<COLOR>11</COLOR>
		<MINQTY>9</MINQTY>
	</ITEM>
	<ITEM>
		<ITEMTYPE>P</ITEMTYPE>
		<ITEMID>3707</ITEMID>
		<COLOR>11</COLOR>
		<MINQTY>5</MINQTY>
	</ITEM>
	<ITEM>
		<ITEMTYPE>P</ITEMTYPE>
		<ITEMID>3708</ITEMID>
		<COLOR>11</COLOR>
		<MINQTY>5</MINQTY>
	</ITEM>
	<ITEM>
		<ITEMTYPE>P</ITEMTYPE>
		<ITEMID>3713</ITEMID>
		<COLOR>86</COLOR>
		<MINQTY>65</MINQTY>
	</ITEM>
	<ITEM>
		<ITEMTYPE>P</ITEMTYPE>
		<ITEMID>3737</ITEMID>
		<COLOR>11</COLOR>
		<MINQTY>5</MINQTY>
	</ITEM>
	<ITEM>
		<ITEMTYPE>P</ITEMTYPE>
		<ITEMID>3749</ITEMID>
		<COLOR>2</COLOR>
		<MINQTY>22</MINQTY>
	</ITEM>
	<ITEM>
		<ITEMTYPE>P</ITEMTYPE>
		<ITEMID>4185</ITEMID>
		<COLOR>85</COLOR>
		<MINQTY>8</MINQTY>
	</ITEM>
	<ITEM>
		<ITEMTYPE>P</ITEMTYPE>
		<ITEMID>4265c</ITEMID>
		<COLOR>3</COLOR>
		<MINQTY>37</MINQTY>
	</ITEM>
	<ITEM>
		<ITEMTYPE>P</ITEMTYPE>
		<ITEMID>2780</ITEMID>
		<COLOR>11</COLOR>
		<MINQTY>292</MINQTY>
	</ITEM>
	<ITEM>
		<ITEMTYPE>P</ITEMTYPE>
		<ITEMID>32526</ITEMID>
		<COLOR>1</COLOR>
		<MINQTY>8</MINQTY>
	</ITEM>
	<ITEM>
		<ITEMTYPE>P</ITEMTYPE>
		<ITEMID>32526</ITEMID>
		<COLOR>86</COLOR>
		<MINQTY>10</MINQTY>
	</ITEM>
	<ITEM>
		<ITEMTYPE>P</ITEMTYPE>
		<ITEMID>32184</ITEMID>
		<COLOR>11</COLOR>
		<MINQTY>20</MINQTY>
	</ITEM>
	<ITEM>
		<ITEMTYPE>P</ITEMTYPE>
		<ITEMID>32291</ITEMID>
		<COLOR>11</COLOR>
		<MINQTY>8</MINQTY>
	</ITEM>
	<ITEM>
		<ITEMTYPE>P</ITEMTYPE>
		<ITEMID>32278</ITEMID>
		<COLOR>1</COLOR>
		<MINQTY>25</MINQTY>
	</ITEM>
	<ITEM>
		<ITEMTYPE>P</ITEMTYPE>
		<ITEMID>4519</ITEMID>
		<COLOR>86</COLOR>
		<MINQTY>40</MINQTY>
	</ITEM>
	<ITEM>
		<ITEMTYPE>P</ITEMTYPE>
		<ITEMID>6536</ITEMID>
		<COLOR>86</COLOR>
		<MINQTY>20</MINQTY>
	</ITEM>
	<ITEM>
		<ITEMTYPE>P</ITEMTYPE>
		<ITEMID>6558</ITEMID>
		<COLOR>7</COLOR>
		<MINQTY>67</MINQTY>
	</ITEM>
	<ITEM>
		<ITEMTYPE>P</ITEMTYPE>
		<ITEMID>6587</ITEMID>
		<COLOR>69</COLOR>
		<MINQTY>20</MINQTY>
	</ITEM>
	<ITEM>
		<ITEMTYPE>P</ITEMTYPE>
		<ITEMID>6589</ITEMID>
		<COLOR>2</COLOR>
		<MINQTY>8</MINQTY>
	</ITEM>
	<ITEM>
		<ITEMTYPE>P</ITEMTYPE>
		<ITEMID>6629</ITEMID>
		<COLOR>11</COLOR>
		<MINQTY>10</MINQTY>
	</ITEM>
	<ITEM>
		<ITEMTYPE>P</ITEMTYPE>
		<ITEMID>2815</ITEMID>
		<COLOR>11</COLOR>
		<MINQTY>8</MINQTY>
	</ITEM>
	<ITEM>
		<ITEMTYPE>P</ITEMTYPE>
		<ITEMID>32271</ITEMID>
		<COLOR>86</COLOR>
		<MINQTY>8</MINQTY>
	</ITEM>
	<ITEM>
		<ITEMTYPE>P</ITEMTYPE>
		<ITEMID>32316</ITEMID>
		<COLOR>86</COLOR>
		<MINQTY>15</MINQTY>
	</ITEM>
	<ITEM>
		<ITEMTYPE>P</ITEMTYPE>
		<ITEMID>32270</ITEMID>
		<COLOR>11</COLOR>
		<MINQTY>6</MINQTY>
	</ITEM>
	<ITEM>
		<ITEMTYPE>P</ITEMTYPE>
		<ITEMID>32269</ITEMID>
		<COLOR>11</COLOR>
		<MINQTY>5</MINQTY>
	</ITEM>
	<ITEM>
		<ITEMTYPE>P</ITEMTYPE>
		<ITEMID>32523</ITEMID>
		<COLOR>3</COLOR>
		<MINQTY>8</MINQTY>
	</ITEM>
	<ITEM>
		<ITEMTYPE>P</ITEMTYPE>
		<ITEMID>32523</ITEMID>
		<COLOR>5</COLOR>
		<MINQTY>10</MINQTY>
	</ITEM>
	<ITEM>
		<ITEMTYPE>P</ITEMTYPE>
		<ITEMID>32523</ITEMID>
		<COLOR>6</COLOR>
		<MINQTY>8</MINQTY>
	</ITEM>
	<ITEM>
		<ITEMTYPE>P</ITEMTYPE>
		<ITEMID>32523</ITEMID>
		<COLOR>7</COLOR>
		<MINQTY>8</MINQTY>
	</ITEM>
	<ITEM>
		<ITEMTYPE>P</ITEMTYPE>
		<ITEMID>32523</ITEMID>
		<COLOR>11</COLOR>
		<MINQTY>4</MINQTY>
	</ITEM>
	<ITEM>
		<ITEMTYPE>P</ITEMTYPE>
		<ITEMID>32449</ITEMID>
		<COLOR>11</COLOR>
		<MINQTY>4</MINQTY>
	</ITEM>
	<ITEM>
		<ITEMTYPE>P</ITEMTYPE>
		<ITEMID>32556</ITEMID>
		<COLOR>2</COLOR>
		<MINQTY>26</MINQTY>
	</ITEM>
	<ITEM>
		<ITEMTYPE>P</ITEMTYPE>
		<ITEMID>32524</ITEMID>
		<COLOR>86</COLOR>
		<MINQTY>25</MINQTY>
	</ITEM>
	<ITEM>
		<ITEMTYPE>P</ITEMTYPE>
		<ITEMID>32072</ITEMID>
		<COLOR>11</COLOR>
		<MINQTY>8</MINQTY>
	</ITEM>
	<ITEM>
		<ITEMTYPE>P</ITEMTYPE>
		<ITEMID>33299</ITEMID>
		<COLOR>11</COLOR>
		<MINQTY>5</MINQTY>
	</ITEM>
	<ITEM>
		<ITEMTYPE>P</ITEMTYPE>
		<ITEMID>x346</ITEMID>
		<COLOR>1</COLOR>
		<MINQTY>9</MINQTY>
	</ITEM>
	<ITEM>
		<ITEMTYPE>P</ITEMTYPE>
		<ITEMID>32525</ITEMID>
		<COLOR>86</COLOR>
		<MINQTY>14</MINQTY>
	</ITEM>
	<ITEM>
		<ITEMTYPE>P</ITEMTYPE>
		<ITEMID>40490</ITEMID>
		<COLOR>86</COLOR>
		<MINQTY>19</MINQTY>
	</ITEM>
	<ITEM>
		<ITEMTYPE>P</ITEMTYPE>
		<ITEMID>41678</ITEMID>
		<COLOR>11</COLOR>
		<MINQTY>8</MINQTY>
	</ITEM>
	<ITEM>
		<ITEMTYPE>P</ITEMTYPE>
		<ITEMID>43093</ITEMID>
		<COLOR>7</COLOR>
		<MINQTY>99</MINQTY>
	</ITEM>
	<ITEM>
		<ITEMTYPE>P</ITEMTYPE>
		<ITEMID>32498</ITEMID>
		<COLOR>11</COLOR>
		<MINQTY>4</MINQTY>
	</ITEM>
	<ITEM>
		<ITEMTYPE>P</ITEMTYPE>
		<ITEMID>41897</ITEMID>
		<COLOR>11</COLOR>
		<MINQTY>6</MINQTY>
	</ITEM>
	<ITEM>
		<ITEMTYPE>P</ITEMTYPE>
		<ITEMID>44294</ITEMID>
		<COLOR>86</COLOR>
		<MINQTY>12</MINQTY>
	</ITEM>
	<ITEM>
		<ITEMTYPE>P</ITEMTYPE>
		<ITEMID>42003</ITEMID>
		<COLOR>85</COLOR>
		<MINQTY>20</MINQTY>
	</ITEM>
	<ITEM>
		<ITEMTYPE>P</ITEMTYPE>
		<ITEMID>45590</ITEMID>
		<COLOR>11</COLOR>
		<MINQTY>8</MINQTY>
	</ITEM>
	<ITEM>
		<ITEMTYPE>P</ITEMTYPE>
		<ITEMID>44809</ITEMID>
		<COLOR>5</COLOR>
		<MINQTY>3</MINQTY>
	</ITEM>
	<ITEM>
		<ITEMTYPE>P</ITEMTYPE>
		<ITEMID>48989</ITEMID>
		<COLOR>86</COLOR>
		<MINQTY>26</MINQTY>
	</ITEM>
	<ITEM>
		<ITEMTYPE>P</ITEMTYPE>
		<ITEMID>41239</ITEMID>
		<COLOR>86</COLOR>
		<MINQTY>12</MINQTY>
	</ITEM>
	<ITEM>
		<ITEMTYPE>P</ITEMTYPE>
		<ITEMID>55615</ITEMID>
		<COLOR>86</COLOR>
		<MINQTY>13</MINQTY>
	</ITEM>
	<ITEM>
		<ITEMTYPE>P</ITEMTYPE>
		<ITEMID>55805</ITEMID>
		<COLOR>11</COLOR>
		<MINQTY>4</MINQTY>
	</ITEM>
	<ITEM>
		<ITEMTYPE>P</ITEMTYPE>
		<ITEMID>55806</ITEMID>
		<COLOR>11</COLOR>
		<MINQTY>2</MINQTY>
	</ITEM>
	<ITEM>
		<ITEMTYPE>P</ITEMTYPE>
		<ITEMID>57518</ITEMID>
		<COLOR>11</COLOR>
		<MINQTY>113</MINQTY>
	</ITEM>
	<ITEM>
		<ITEMTYPE>P</ITEMTYPE>
		<ITEMID>55013</ITEMID>
		<COLOR>85</COLOR>
		<MINQTY>10</MINQTY>
	</ITEM>
	<ITEM>
		<ITEMTYPE>P</ITEMTYPE>
		<ITEMID>6538c</ITEMID>
		<COLOR>5</COLOR>
		<MINQTY>16</MINQTY>
	</ITEM>
	<ITEM>
		<ITEMTYPE>P</ITEMTYPE>
		<ITEMID>57585</ITEMID>
		<COLOR>86</COLOR>
		<MINQTY>4</MINQTY>
	</ITEM>
	<ITEM>
		<ITEMTYPE>P</ITEMTYPE>
		<ITEMID>57519</ITEMID>
		<COLOR>11</COLOR>
		<MINQTY>10</MINQTY>
	</ITEM>
	<ITEM>
		<ITEMTYPE>P</ITEMTYPE>
		<ITEMID>62462</ITEMID>
		<COLOR>86</COLOR>
		<MINQTY>10</MINQTY>
	</ITEM>
	<ITEM>
		<ITEMTYPE>P</ITEMTYPE>
		<ITEMID>60483</ITEMID>
		<COLOR>11</COLOR>
		<MINQTY>16</MINQTY>
	</ITEM>
	<ITEM>
		<ITEMTYPE>P</ITEMTYPE>
		<ITEMID>60484</ITEMID>
		<COLOR>11</COLOR>
		<MINQTY>10</MINQTY>
	</ITEM>
	<ITEM>
		<ITEMTYPE>P</ITEMTYPE>
		<ITEMID>60485</ITEMID>
		<COLOR>86</COLOR>
		<MINQTY>9</MINQTY>
	</ITEM>
	<ITEM>
		<ITEMTYPE>P</ITEMTYPE>
		<ITEMID>63869</ITEMID>
		<COLOR>86</COLOR>
		<MINQTY>14</MINQTY>
	</ITEM>
	<ITEM>
		<ITEMTYPE>P</ITEMTYPE>
		<ITEMID>64179</ITEMID>
		<COLOR>86</COLOR>
		<MINQTY>15</MINQTY>
	</ITEM>
	<ITEM>
		<ITEMTYPE>P</ITEMTYPE>
		<ITEMID>64178</ITEMID>
		<COLOR>86</COLOR>
		<MINQTY>4</MINQTY>
	</ITEM>
	<ITEM>
		<ITEMTYPE>P</ITEMTYPE>
		<ITEMID>64392</ITEMID>
		<COLOR>11</COLOR>
		<MINQTY>2</MINQTY>
	</ITEM>
	<ITEM>
		<ITEMTYPE>P</ITEMTYPE>
		<ITEMID>64682</ITEMID>
		<COLOR>11</COLOR>
		<MINQTY>2</MINQTY>
	</ITEM>
	<ITEM>
		<ITEMTYPE>P</ITEMTYPE>
		<ITEMID>87083</ITEMID>
		<COLOR>85</COLOR>
		<MINQTY>13</MINQTY>
	</ITEM>
	<ITEM>
		<ITEMTYPE>P</ITEMTYPE>
		<ITEMID>87080</ITEMID>
		<COLOR>11</COLOR>
		<MINQTY>3</MINQTY>
	</ITEM>
	<ITEM>
		<ITEMTYPE>P</ITEMTYPE>
		<ITEMID>87082</ITEMID>
		<COLOR>86</COLOR>
		<MINQTY>10</MINQTY>
	</ITEM>
	<ITEM>
		<ITEMTYPE>P</ITEMTYPE>
		<ITEMID>87086</ITEMID>
		<COLOR>11</COLOR>
		<MINQTY>3</MINQTY>
	</ITEM>
	<ITEM>
		<ITEMTYPE>P</ITEMTYPE>
		<ITEMID>94925</ITEMID>
		<COLOR>86</COLOR>
		<MINQTY>8</MINQTY>
	</ITEM>
	<ITEM>
		<ITEMTYPE>P</ITEMTYPE>
		<ITEMID>56908</ITEMID>
		<COLOR>86</COLOR>
		<MINQTY>6</MINQTY>
	</ITEM>
	<ITEM>
		<ITEMTYPE>P</ITEMTYPE>
		<ITEMID>92911</ITEMID>
		<COLOR>85</COLOR>
		<MINQTY>3</MINQTY>
	</ITEM>
	<ITEM>
		<ITEMTYPE>P</ITEMTYPE>
		<ITEMID>99010</ITEMID>
		<COLOR>11</COLOR>
		<MINQTY>4</MINQTY>
	</ITEM>
	<ITEM>
		<ITEMTYPE>P</ITEMTYPE>
		<ITEMID>99009</ITEMID>
		<COLOR>86</COLOR>
		<MINQTY>4</MINQTY>
	</ITEM>
	<ITEM>
		<ITEMTYPE>P</ITEMTYPE>
		<ITEMID>99773</ITEMID>
		<COLOR>86</COLOR>
		<MINQTY>12</MINQTY>
	</ITEM>
	<ITEM>
		<ITEMTYPE>P</ITEMTYPE>
		<ITEMID>10928</ITEMID>
		<COLOR>85</COLOR>
		<MINQTY>9</MINQTY>
	</ITEM>
	<ITEM>
		<ITEMTYPE>P</ITEMTYPE>
		<ITEMID>95646c01</ITEMID>
		<COLOR>0</COLOR>
		<MINQTY>2</MINQTY>
	</ITEM>
	<ITEM>
		<ITEMTYPE>P</ITEMTYPE>
		<ITEMID>95658</ITEMID>
		<COLOR>0</COLOR>
		<MINQTY>4</MINQTY>
	</ITEM>
	<ITEM>
		<ITEMTYPE>P</ITEMTYPE>
		<ITEMID>99455</ITEMID>
		<COLOR>0</COLOR>
		<MINQTY>2</MINQTY>
	</ITEM>
	<ITEM>
		<ITEMTYPE>P</ITEMTYPE>
		<ITEMID>95652</ITEMID>
		<COLOR>0</COLOR>
		<MINQTY>2</MINQTY>
	</ITEM>
	<ITEM>
		<ITEMTYPE>P</ITEMTYPE>
		<ITEMID>99380</ITEMID>
		<COLOR>0</COLOR>
		<MINQTY>2</MINQTY>
	</ITEM>
	<ITEM>
		<ITEMTYPE>P</ITEMTYPE>
		<ITEMID>95650</ITEMID>
		<COLOR>0</COLOR>
		<MINQTY>2</MINQTY>
	</ITEM>
	<ITEM>
		<ITEMTYPE>P</ITEMTYPE>
		<ITEMID>95648</ITEMID>
		<COLOR>0</COLOR>
		<MINQTY>4</MINQTY>
	</ITEM>
	<ITEM>
		<ITEMTYPE>P</ITEMTYPE>
		<ITEMID>95656</ITEMID>
		<COLOR>86</COLOR>
		<MINQTY>2</MINQTY>
	</ITEM>
	<ITEM>
		<ITEMTYPE>P</ITEMTYPE>
		<ITEMID>99948</ITEMID>
		<COLOR>0</COLOR>
		<MINQTY>2</MINQTY>
	</ITEM>
	<ITEM>
		<ITEMTYPE>P</ITEMTYPE>
		<ITEMID>4716</ITEMID>
		<COLOR>86</COLOR>
		<MINQTY>5</MINQTY>
	</ITEM>
<ITEM>
		<ITEMTYPE>P</ITEMTYPE>
		<ITEMID>4589b</ITEMID>
		<COLOR>17</COLOR>
		<MINQTY>4</MINQTY>
	</ITEM>
	<ITEM>
		<ITEMTYPE>P</ITEMTYPE>
		<ITEMID>x346</ITEMID>
		<COLOR>5</COLOR>
		<MINQTY>2</MINQTY>
	</ITEM>
	<ITEM>
		<ITEMTYPE>P</ITEMTYPE>
		<ITEMID>3941</ITEMID>
		<COLOR>16</COLOR>
		<MINQTY>2</MINQTY>
	</ITEM>
	<ITEM>
		<ITEMTYPE>P</ITEMTYPE>
		<ITEMID>3941</ITEMID>
		<COLOR>15</COLOR>
		<MINQTY>2</MINQTY>
	</ITEM>
	<ITEM>
		<ITEMTYPE>P</ITEMTYPE>
		<ITEMID>98578</ITEMID>
		<COLOR>14</COLOR>
		<MINQTY>2</MINQTY>
	</ITEM>
	<ITEM>
		<ITEMTYPE>P</ITEMTYPE>
		<ITEMID>57539</ITEMID>
		<COLOR>95</COLOR>
		<MINQTY>2</MINQTY>
	</ITEM>
	<ITEM>
		<ITEMTYPE>P</ITEMTYPE>
		<ITEMID>78c19</ITEMID>
		<COLOR>15</COLOR>
		<MINQTY>4</MINQTY>
	</ITEM>
	<ITEM>
		<ITEMTYPE>P</ITEMTYPE>
		<ITEMID>4032</ITEMID>
		<COLOR>11</COLOR>
		<MINQTY>4</MINQTY>
	</ITEM>
	<ITEM>
		<ITEMTYPE>P</ITEMTYPE>
		<ITEMID>2654</ITEMID>
		<COLOR>11</COLOR>
		<MINQTY>2</MINQTY>
	</ITEM>
	<ITEM>
		<ITEMTYPE>P</ITEMTYPE>
		<ITEMID>x71</ITEMID>
		<COLOR>1</COLOR>
		<MINQTY>2</MINQTY>
	</ITEM>
	<ITEM>
		<ITEMTYPE>P</ITEMTYPE>
		<ITEMID>x37</ITEMID>
		<COLOR>5</COLOR>
		<MINQTY>2</MINQTY>
	</ITEM>
	<ITEM>
		<ITEMTYPE>P</ITEMTYPE>
		<ITEMID>x89</ITEMID>
		<COLOR>7</COLOR>
		<MINQTY>2</MINQTY>
	</ITEM>
	<ITEM>
		<ITEMTYPE>P</ITEMTYPE>
		<ITEMID>x90</ITEMID>
		<COLOR>3</COLOR>
		<MINQTY>2</MINQTY>
	</ITEM>
	<ITEM>
		<ITEMTYPE>P</ITEMTYPE>
		<ITEMID>6575</ITEMID>
		<COLOR>85</COLOR>
		<MINQTY>2</MINQTY>
	</ITEM>
	<ITEM>
		<ITEMTYPE>P</ITEMTYPE>
		<ITEMID>6641</ITEMID>
		<COLOR>5</COLOR>
		<MINQTY>1</MINQTY>
	</ITEM>
	<ITEM>
		<ITEMTYPE>P</ITEMTYPE>
		<ITEMID>6539</ITEMID>
		<COLOR>5</COLOR>
		<MINQTY>1</MINQTY>
	</ITEM>
	<ITEM>
		<ITEMTYPE>P</ITEMTYPE>
		<ITEMID>48452</ITEMID>
		<COLOR>86</COLOR>
		<MINQTY>1</MINQTY>
	</ITEM>
	<ITEM>
		<ITEMTYPE>P</ITEMTYPE>
		<ITEMID>48168</ITEMID>
		<COLOR>11</COLOR>
		<MINQTY>1</MINQTY>
	</ITEM>
	<ITEM>
		<ITEMTYPE>P</ITEMTYPE>
		<ITEMID>2736</ITEMID>
		<COLOR>86</COLOR>
		<MINQTY>2</MINQTY>
	</ITEM>
	<ITEM>
		<ITEMTYPE>P</ITEMTYPE>
		<ITEMID>6553</ITEMID>
		<COLOR>85</COLOR>
		<MINQTY>2</MINQTY>
	</ITEM>
	<ITEM>
		<ITEMTYPE>P</ITEMTYPE>
		<ITEMID>99008</ITEMID>
		<COLOR>2</COLOR>
		<MINQTY>2</MINQTY>
	</ITEM>
	<ITEM>
		<ITEMTYPE>P</ITEMTYPE>
		<ITEMID>32209</ITEMID>
		<COLOR>85</COLOR>
		<MINQTY>4</MINQTY>
	</ITEM>
	<ITEM>
		<ITEMTYPE>P</ITEMTYPE>
		<ITEMID>32016</ITEMID>
		<COLOR>11</COLOR>
		<MINQTY>4</MINQTY>
	</ITEM>
	<ITEM>
		<ITEMTYPE>P</ITEMTYPE>
		<ITEMID>32015</ITEMID>
		<COLOR>11</COLOR>
		<MINQTY>3</MINQTY>
	</ITEM>
	<ITEM>
		<ITEMTYPE>P</ITEMTYPE>
		<ITEMID>10288</ITEMID>
		<COLOR>120</COLOR>
		<MINQTY>5</MINQTY>
	</ITEM>
	<ITEM>
		<ITEMTYPE>P</ITEMTYPE>
		<ITEMID>10197</ITEMID>
		<COLOR>85</COLOR>
		<MINQTY>2</MINQTY>
	</ITEM>
	<ITEM>
		<ITEMTYPE>P</ITEMTYPE>
		<ITEMID>98989</ITEMID>
		<COLOR>86</COLOR>
		<MINQTY>3</MINQTY>
	</ITEM>
	<ITEM>
		<ITEMTYPE>P</ITEMTYPE>
		<ITEMID>6538b</ITEMID>
		<COLOR>2</COLOR>
		<MINQTY>1</MINQTY>
	</ITEM>
	<ITEM>
		<ITEMTYPE>P</ITEMTYPE>
		<ITEMID>98585</ITEMID>
		<COLOR>15</COLOR>
		<MINQTY>2</MINQTY>
	</ITEM>
	<ITEM>
		<ITEMTYPE>P</ITEMTYPE>
		<ITEMID>32039</ITEMID>
		<COLOR>11</COLOR>
		<MINQTY>22</MINQTY>
	</ITEM>
	<ITEM>
		<ITEMTYPE>P</ITEMTYPE>
		<ITEMID>6542b</ITEMID>
		<COLOR>85</COLOR>
		<MINQTY>2</MINQTY>
	</ITEM>
	<ITEM>
		<ITEMTYPE>P</ITEMTYPE>
		<ITEMID>32198</ITEMID>
		<COLOR>2</COLOR>
		<MINQTY>1</MINQTY>
	</ITEM>
	<ITEM>
		<ITEMTYPE>P</ITEMTYPE>
		<ITEMID>87407</ITEMID>
		<COLOR>86</COLOR>
		<MINQTY>2</MINQTY>
	</ITEM>
	<ITEM>
		<ITEMTYPE>P</ITEMTYPE>
		<ITEMID>62821b</ITEMID>
		<COLOR>85</COLOR>
		<MINQTY>1</MINQTY>
	</ITEM>
	<ITEM>
		<ITEMTYPE>P</ITEMTYPE>
		<ITEMID>64781</ITEMID>
		<COLOR>11</COLOR>
		<MINQTY>2</MINQTY>
	</ITEM>
	<ITEM>
		<ITEMTYPE>P</ITEMTYPE>
		<ITEMID>43857</ITEMID>
		<COLOR>86</COLOR>
		<MINQTY>3</MINQTY>
	</ITEM>
	<ITEM>
		<ITEMTYPE>P</ITEMTYPE>
		<ITEMID>41677</ITEMID>
		<COLOR>11</COLOR>
		<MINQTY>2</MINQTY>
	</ITEM>
	<ITEM>
		<ITEMTYPE>P</ITEMTYPE>
		<ITEMID>41677</ITEMID>
		<COLOR>86</COLOR>
		<MINQTY>1</MINQTY>
	</ITEM>
	<ITEM>
		<ITEMTYPE>P</ITEMTYPE>
		<ITEMID>32523</ITEMID>
		<COLOR>86</COLOR>
		<MINQTY>10</MINQTY>
	</ITEM>
	<ITEM>
		<ITEMTYPE>P</ITEMTYPE>
		<ITEMID>32523</ITEMID>
		<COLOR>1</COLOR>
		<MINQTY>1</MINQTY>
	</ITEM>
	<ITEM>
		<ITEMTYPE>P</ITEMTYPE>
		<ITEMID>6632</ITEMID>
		<COLOR>86</COLOR>
		<MINQTY>6</MINQTY>
	</ITEM>
	<ITEM>
		<ITEMTYPE>P</ITEMTYPE>
		<ITEMID>11478</ITEMID>
		<COLOR>11</COLOR>
		<MINQTY>4</MINQTY>
	</ITEM>
	<ITEM>
		<ITEMTYPE>P</ITEMTYPE>
		<ITEMID>2739a</ITEMID>
		<COLOR>85</COLOR>
		<MINQTY>2</MINQTY>
	</ITEM>
	<ITEM>
		<ITEMTYPE>P</ITEMTYPE>
		<ITEMID>32009</ITEMID>
		<COLOR>86</COLOR>
		<MINQTY>5</MINQTY>
	</ITEM>
	<ITEM>
		<ITEMTYPE>P</ITEMTYPE>
		<ITEMID>32140</ITEMID>
		<COLOR>86</COLOR>
		<MINQTY>8</MINQTY>
	</ITEM>
	<ITEM>
		<ITEMTYPE>P</ITEMTYPE>
		<ITEMID>14149</ITEMID>
		<COLOR>5</COLOR>
		<MINQTY>27</MINQTY>
	</ITEM>
	<ITEM>
		<ITEMTYPE>P</ITEMTYPE>
		<ITEMID>11954</ITEMID>
		<COLOR>11</COLOR>
		<MINQTY>4</MINQTY>
	</ITEM>
	<ITEM>
		<ITEMTYPE>P</ITEMTYPE>
		<ITEMID>64683</ITEMID>
		<COLOR>11</COLOR>
		<MINQTY>2</MINQTY>
	</ITEM>
	<ITEM>
		<ITEMTYPE>P</ITEMTYPE>
		<ITEMID>64391</ITEMID>
		<COLOR>11</COLOR>
		<MINQTY>2</MINQTY>
	</ITEM>
	<ITEM>
		<ITEMTYPE>P</ITEMTYPE>
		<ITEMID>64681</ITEMID>
		<COLOR>11</COLOR>
		<MINQTY>1</MINQTY>
	</ITEM>
	<ITEM>
		<ITEMTYPE>P</ITEMTYPE>
		<ITEMID>64393</ITEMID>
		<COLOR>11</COLOR>
		<MINQTY>1</MINQTY>
	</ITEM>
	<ITEM>
		<ITEMTYPE>P</ITEMTYPE>
		<ITEMID>64394</ITEMID>
		<COLOR>11</COLOR>
		<MINQTY>1</MINQTY>
	</ITEM>
	<ITEM>
		<ITEMTYPE>P</ITEMTYPE>
		<ITEMID>64680</ITEMID>
		<COLOR>11</COLOR>
		<MINQTY>1</MINQTY>
	</ITEM>
	<ITEM>
		<ITEMTYPE>P</ITEMTYPE>
		<ITEMID>11946</ITEMID>
		<COLOR>5</COLOR>
		<MINQTY>2</MINQTY>
	</ITEM>
	<ITEM>
		<ITEMTYPE>P</ITEMTYPE>
		<ITEMID>11947</ITEMID>
		<COLOR>5</COLOR>
		<MINQTY>2</MINQTY>
	</ITEM>
	<ITEM>
		<ITEMTYPE>P</ITEMTYPE>
		<ITEMID>32002</ITEMID>
		<COLOR>2</COLOR>
		<MINQTY>6</MINQTY>
	</ITEM>
	<ITEM>
		<ITEMTYPE>P</ITEMTYPE>
		<ITEMID>32557</ITEMID>
		<COLOR>86</COLOR>
		<MINQTY>4</MINQTY>
	</ITEM>
	<ITEM>
		<ITEMTYPE>P</ITEMTYPE>
		<ITEMID>87408</ITEMID>
		<COLOR>11</COLOR>
		<MINQTY>1</MINQTY>
	</ITEM>
	<ITEM>
		<ITEMTYPE>P</ITEMTYPE>
		<ITEMID>32138</ITEMID>
		<COLOR>11</COLOR>
		<MINQTY>4</MINQTY>
	</ITEM>
	<ITEM>
		<ITEMTYPE>P</ITEMTYPE>
		<ITEMID>6628a</ITEMID>
		<COLOR>11</COLOR>
		<MINQTY>8</MINQTY>
	</ITEM>
	<ITEM>
		<ITEMTYPE>P</ITEMTYPE>
		<ITEMID>92910</ITEMID>
		<COLOR>86</COLOR>
		<MINQTY>1</MINQTY>
	</ITEM>
	<ITEM>
		<ITEMTYPE>P</ITEMTYPE>
		<ITEMID>32494</ITEMID>
		<COLOR>86</COLOR>
		<MINQTY>2</MINQTY>
	</ITEM>
	<ITEM>
		<ITEMTYPE>P</ITEMTYPE>
		<ITEMID>92906</ITEMID>
		<COLOR>85</COLOR>
		<MINQTY>2</MINQTY>
	</ITEM>
	<ITEM>
		<ITEMTYPE>P</ITEMTYPE>
		<ITEMID>92908</ITEMID>
		<COLOR>86</COLOR>
		<MINQTY>2</MINQTY>
	</ITEM>
	<ITEM>
		<ITEMTYPE>P</ITEMTYPE>
		<ITEMID>92909</ITEMID>
		<COLOR>85</COLOR>
		<MINQTY>2</MINQTY>
	</ITEM>
	<ITEM>
		<ITEMTYPE>P</ITEMTYPE>
		<ITEMID>62520c01</ITEMID>
		<COLOR>86</COLOR>
		<MINQTY>2</MINQTY>
	</ITEM>
	<ITEM>
		<ITEMTYPE>P</ITEMTYPE>
		<ITEMID>98138</ITEMID>
		<COLOR>17</COLOR>
		<MINQTY>7</MINQTY>
	</ITEM>
	<ITEM>
		<ITEMTYPE>P</ITEMTYPE>
		<ITEMID>44309</ITEMID>
		<COLOR>11</COLOR>
		<MINQTY>2</MINQTY>
	</ITEM>
	<ITEM>
		<ITEMTYPE>P</ITEMTYPE>
		<ITEMID>44771</ITEMID>
		<COLOR>11</COLOR>
		<MINQTY>4</MINQTY>
	</ITEM>
	<ITEM>
		<ITEMTYPE>P</ITEMTYPE>
		<ITEMID>89201</ITEMID>
		<COLOR>11</COLOR>
		<MINQTY>2</MINQTY>
	</ITEM>
	<ITEM>
		<ITEMTYPE>P</ITEMTYPE>
		<ITEMID>42610</ITEMID>
		<COLOR>86</COLOR>
		<MINQTY>7</MINQTY>
	</ITEM>
	<ITEM>
		<ITEMTYPE>P</ITEMTYPE>
		<ITEMID>56902</ITEMID>
		<COLOR>86</COLOR>
		<MINQTY>1</MINQTY>
	</ITEM>
	<ITEM>
		<ITEMTYPE>P</ITEMTYPE>
		<ITEMID>55982</ITEMID>
		<COLOR>86</COLOR>
		<MINQTY>5</MINQTY>
	</ITEM>
	<ITEM>
		<ITEMTYPE>P</ITEMTYPE>
		<ITEMID>56145</ITEMID>
		<COLOR>86</COLOR>
		<MINQTY>3</MINQTY>
	</ITEM>
	<ITEM>
		<ITEMTYPE>P</ITEMTYPE>
		<ITEMID>15038</ITEMID>
		<COLOR>86</COLOR>
		<MINQTY>4</MINQTY>
	</ITEM>
</INVENTORY>